tests/__init__.py
tests/test_client.py
weavium/__init__.py
weavium/client.py
weavium/instrumentation.py
weavium-0.1.6.dist-info/licenses/LICENSE
weavium-0.1.6.dist-info/METADATA
weavium-0.1.6.dist-info/WHEEL
weavium-0.1.6.dist-info/top_level.txt
weavium-0.1.6.dist-info/RECORD
