Metadata-Version: 2.4
Name: weavium
Version: 0.1.6
Summary: Python client library for the Weavium prompt compression API
Author: Weavium Team
Author-email: Weavium Team <support@weavium.com>
Maintainer-email: Weavium Team <support@weavium.com>
License: MIT
Project-URL: Homepage, https://weavium.com
Project-URL: Documentation, https://docs.weavium.com
Project-URL: Repository, https://github.com/weavium/weavium-ai
Project-URL: Issues, https://github.com/weavium/weavium-ai/issues
Project-URL: API Documentation, https://api.weavium.com/docs
Project-URL: Changelog, https://github.com/weavium/weavium-ai/blob/main/python_client/CHANGELOG.md
Keywords: weavium,api,client,compression,llm,prompt,ai,machine-learning
Classifier: Development Status :: 3 - Alpha
Classifier: Intended Audience :: Developers
Classifier: License :: OSI Approved :: MIT License
Classifier: Operating System :: OS Independent
Classifier: Programming Language :: Python :: 3
Classifier: Programming Language :: Python :: 3.8
Classifier: Programming Language :: Python :: 3.9
Classifier: Programming Language :: Python :: 3.10
Classifier: Programming Language :: Python :: 3.11
Classifier: Programming Language :: Python :: 3.12
Classifier: Topic :: Software Development :: Libraries :: Python Modules
Classifier: Topic :: Internet :: WWW/HTTP :: HTTP Servers
Classifier: Topic :: Scientific/Engineering :: Artificial Intelligence
Requires-Python: >=3.8
License-File: LICENSE
Requires-Dist: requests>=2.25.0
Provides-Extra: boto3
Requires-Dist: boto3>=1.26.0; extra == "boto3"
Provides-Extra: dev
Requires-Dist: pytest>=6.0; extra == "dev"
Requires-Dist: pytest-cov>=2.0; extra == "dev"
Requires-Dist: black>=21.0; extra == "dev"
Requires-Dist: flake8>=3.9; extra == "dev"
Requires-Dist: mypy>=0.900; extra == "dev"
Requires-Dist: boto3>=1.26.0; extra == "dev"
Requires-Dist: vcrpy>=4.0.0; extra == "dev"
Dynamic: author
Dynamic: license-file
Dynamic: requires-python
